{
    "checksum": "1cb98538772e49fffee338c966dc5044",
    "wallpaper": "/home/kito/.config/wpg/wallpapers/464961953_122167760798257834_1224512128540262863_n.jpg",
    "alpha": "100",
    "special": {
        "background": "#1c1f1c",
        "foreground": "#c6c7c6",
        "cursor": "#c6c7c6"
    },
    "colors": {
        "color0": "#1c1f1c",
        "color1": "#6E778C",
        "color2": "#6C9C95",
        "color3": "#74C5B2",
        "color4": "#69BAE6",
        "color5": "#919AAE",
        "color6": "#99A3B7",
        "color7": "#c6c7c6",
        "color8": "#617661",
        "color9": "#6E778C",
        "color10": "#6C9C95",
        "color11": "#74C5B2",
        "color12": "#69BAE6",
        "color13": "#919AAE",
        "color14": "#99A3B7",
        "color15": "#c6c7c6"
    }
}